{
	"list": [
		{
			"id": 1,
			"content": "세계 여행하기"
		},
		{
			"id": 2,
			"content": "점심 먹기1"
		},
		{
			"id": 3,
			"content": "점심 먹기2"
		},
		{
			"id": 4,
			"content": "점심 먹기3"
		},
		{
			"id": 5,
			"content": "점심 먹기4"
		},
		{
			"id": 6,
			"content": "점심 먹기5"
		},
		{
			"id": 7,
			"content": "점심 먹기6"
		},
		{
			"id": 8,
			"content": "점심 먹기7"
		},
		{
			"id": 9,
			"content": "세계 여행하기"
		},
		{
			"id": 10,
			"content": "점심 먹기1"
		},
		{
			"id": 11,
			"content": "점심 먹기2"
		},
		{
			"id": 12,
			"content": "점심 먹기3"
		},
		{
			"id": 13,
			"content": "점심 먹기4"
		},
		{
			"id": 14,
			"content": "점심 먹기5"
		},
		{
			"id": 15,
			"content": "점심 먹기6"
		},
		{
			"id": 16,
			"content": "점심 먹기7"
		},
		{
			"id": 17,
			"content": "세계 여행하기"
		},
		{
			"id": 18,
			"content": "점심 먹기1"
		},
		{
			"id": 19,
			"content": "점심 먹기2"
		},
		{
			"id": 20,
			"content": "점심 먹기3"
		},
		{
			"id": 21,
			"content": "점심 먹기4"
		},
		{
			"id": 22,
			"content": "점심 먹기5"
		},
		{
			"id": 23,
			"content": "점심 먹기6"
		},
		{
			"id": 24,
			"content": "점심 먹기7"
		}
	]}